[
    {
        "name": "David Bowie",
        "date_of_death": "10 January, 2016",
        "first_death_edit": 699258291,
        "base_edit": 699199631
    },
    {
        "name": "Michael Jackson",
        "base_edit": 298631851,
        "first_death_edit": 298632091,
        "date_of_death": "June 25, 2009"
    },
    {
        "name": "Ronald Reagan",
        "base_edit": 3955334,
        "first_death_edit": 3956776,
        "date_of_death": "June 5, 2004"
    },
    {
        "name": "Katharine Hepburn",
        "date_of_death": "June 29, 2003",
        "base_edit": 1094270,
        "first_death_edit": 1094279
    },
    {
        "name": "Osama bin Laden",
        "base_edit": 426997211,
        "first_death_edit": 426997252,
        "date_of_death": "May 2, 2011"
    },
    {
        "name": "Prince (musician)",
        "base_edit": 716414662,
        "first_death_edit": 716414868,
        "date_of_death": "April 21, 2016"
    },
    {
        "name": "Donna Summer",
        "date_of_death": "May 17, 2012",
        "base_edit": 493040889,
        "first_death_edit": 493040905
    },
    {
        "name": "John Glenn",
        "base_edit": 753656269,
        "first_death_edit": 753720457,
        "date_of_death": "December 8, 2016"
    },
    {
        "name": "George Harrison",
        "base_edit": 255117,
        "first_death_edit": 255118,
        "date_of_death": "November 29, 2001"
    },
    {
        "name": "Luc Coene",
        "base_edit": 728456637,
        "first_death_edit": 758614739,
        "date_of_death": "January 5, 2017"
    },
    {
        "name": "Hunter S. Thompson",
        "date_of_death": "February 20, 2005",
        "base_edit": 10484392,
        "first_death_edit": 10484468
    },
    {
        "name": "Dennis Ritchie",
        "date_of_death": "October 12, 2011",
        "base_edit": 453910145,
        "first_death_edit": 455301448
    }
]